{
    "Ahn Jeong-won": {
        "vaderAveragePositive": "0.52075",
        "vaderAverageNeutral": "0.8847647058823529",
        "vaderAverageNegative": "0.5615",
        "vaderMedianPositive": "0.593",
        "vaderMedianNeutral": "1.0",
        "vaderMedianNegative": "0.5615",
        "vaderStdPositive": "0.34420768704109705",
        "vaderStdNeutral": "0.20522793067565573",
        "vaderStdNegative": "0.004949747468305759",
        "vaderPositiveSentencesCount": "12",
        "vaderNeutralSentencesCount": "51",
        "vaderNegativeSentencesCount": "2",
        "roBERTaAveragePositive": "0.6526861",
        "roBERTaAverageNeutral": "0.7427692",
        "roBERTaAverageNegative": "0.58665293",
        "roBERTaMedianPositive": "0.61675084",
        "roBERTaMedianNeutral": "0.7703897",
        "roBERTaMedianNegative": "0.57552224",
        "roBERTaStdPositive": "0.14828318",
        "roBERTaStdNeutral": "0.105338596",
        "roBERTaStdNegative": "0.12024154",
        "roBERTaPositiveSentencesCount": "6",
        "roBERTaNeutralSentencesCount": "54",
        "roBERTaNegativeSentencesCount": "5",
        "TotalSentencesCount": "65"
    },
    "Kim Jun-wan": {
        "vaderAveragePositive": "0.6206744186046511",
        "vaderAverageNeutral": "0.885232044198895",
        "vaderAverageNegative": "0.609875",
        "vaderMedianPositive": "0.625",
        "vaderMedianNeutral": "1.0",
        "vaderMedianNegative": "0.578",
        "vaderStdPositive": "0.24371965949682672",
        "vaderStdNeutral": "0.18264446723596406",
        "vaderStdNegative": "0.15963077188729416",
        "vaderPositiveSentencesCount": "43",
        "vaderNeutralSentencesCount": "181",
        "vaderNegativeSentencesCount": "16",
        "roBERTaAveragePositive": "0.7584327",
        "roBERTaAverageNeutral": "0.7271558",
        "roBERTaAverageNegative": "0.6928783",
        "roBERTaMedianPositive": "0.79858476",
        "roBERTaMedianNeutral": "0.73967624",
        "roBERTaMedianNegative": "0.7023272",
        "roBERTaStdPositive": "0.1594031",
        "roBERTaStdNeutral": "0.10554279",
        "roBERTaStdNegative": "0.12962295",
        "roBERTaPositiveSentencesCount": "25",
        "roBERTaNeutralSentencesCount": "187",
        "roBERTaNegativeSentencesCount": "28",
        "TotalSentencesCount": "240"
    },
    "Lee Ik-joon": {
        "vaderAveragePositive": "0.685025",
        "vaderAverageNeutral": "0.9009615384615385",
        "vaderAverageNegative": "0.6981764705882353",
        "vaderMedianPositive": "0.71",
        "vaderMedianNeutral": "1.0",
        "vaderMedianNegative": "0.688",
        "vaderStdPositive": "0.22512919225442132",
        "vaderStdNeutral": "0.17401731562360853",
        "vaderStdNegative": "0.1722074458662131",
        "vaderPositiveSentencesCount": "40",
        "vaderNeutralSentencesCount": "182",
        "vaderNegativeSentencesCount": "17",
        "roBERTaAveragePositive": "0.7308537",
        "roBERTaAverageNeutral": "0.71291584",
        "roBERTaAverageNegative": "0.7020853",
        "roBERTaMedianPositive": "0.70061827",
        "roBERTaMedianNeutral": "0.72030973",
        "roBERTaMedianNegative": "0.7338815",
        "roBERTaStdPositive": "0.13518628",
        "roBERTaStdNeutral": "0.10443165",
        "roBERTaStdNegative": "0.14535856",
        "roBERTaPositiveSentencesCount": "22",
        "roBERTaNeutralSentencesCount": "198",
        "roBERTaNegativeSentencesCount": "19",
        "TotalSentencesCount": "239"
    },
    "Yang Seok-hyung": {
        "vaderAveragePositive": "0.7578",
        "vaderAverageNeutral": "0.9155555555555556",
        "vaderAverageNegative": "1.0",
        "vaderMedianPositive": "0.75",
        "vaderMedianNeutral": "1.0",
        "vaderMedianNegative": "1.0",
        "vaderStdPositive": "0.16951460114102262",
        "vaderStdNeutral": "0.16758289822585648",
        "vaderStdNegative": "nan",
        "vaderPositiveSentencesCount": "5",
        "vaderNeutralSentencesCount": "9",
        "vaderNegativeSentencesCount": "1",
        "roBERTaAveragePositive": "0.94366604",
        "roBERTaAverageNeutral": "0.6954728",
        "roBERTaAverageNegative": "0.93197227",
        "roBERTaMedianPositive": "0.94366604",
        "roBERTaMedianNeutral": "0.70885557",
        "roBERTaMedianNegative": "0.93197227",
        "roBERTaStdPositive": "nan",
        "roBERTaStdNeutral": "0.087763675",
        "roBERTaStdNegative": "nan",
        "roBERTaPositiveSentencesCount": "1",
        "roBERTaNeutralSentencesCount": "13",
        "roBERTaNegativeSentencesCount": "1",
        "TotalSentencesCount": "15"
    },
    "Chae Song-hwa": {
        "vaderAveragePositive": "0.49794736842105264",
        "vaderAverageNeutral": "0.8924179104477612",
        "vaderAverageNegative": "0.6366666666666666",
        "vaderMedianPositive": "0.589",
        "vaderMedianNeutral": "1.0",
        "vaderMedianNegative": "0.565",
        "vaderStdPositive": "0.2844988720313922",
        "vaderStdNeutral": "0.1926102320556655",
        "vaderStdNegative": "0.17209009268403572",
        "vaderPositiveSentencesCount": "19",
        "vaderNeutralSentencesCount": "67",
        "vaderNegativeSentencesCount": "9",
        "roBERTaAveragePositive": "0.81760675",
        "roBERTaAverageNeutral": "0.6894143",
        "roBERTaAverageNegative": "0.59934753",
        "roBERTaMedianPositive": "0.8383312",
        "roBERTaMedianNeutral": "0.68945074",
        "roBERTaMedianNegative": "0.56570244",
        "roBERTaStdPositive": "0.14848699",
        "roBERTaStdNeutral": "0.11657715",
        "roBERTaStdNegative": "0.08401608",
        "roBERTaPositiveSentencesCount": "8",
        "roBERTaNeutralSentencesCount": "78",
        "roBERTaNegativeSentencesCount": "9",
        "TotalSentencesCount": "95"
    },
    "Secondary": {
        "vaderAveragePositive": "0.6785388349514563",
        "vaderAverageNeutral": "0.9103211678832117",
        "vaderAverageNegative": "0.6415178571428571",
        "vaderMedianPositive": "0.6924999999999999",
        "vaderMedianNeutral": "1.0",
        "vaderMedianNegative": "0.6114999999999999",
        "vaderStdPositive": "0.26286479126062073",
        "vaderStdNeutral": "0.17000955707329216",
        "vaderStdNegative": "0.14963130336948863",
        "vaderPositiveSentencesCount": "206",
        "vaderNeutralSentencesCount": "548",
        "vaderNegativeSentencesCount": "56",
        "roBERTaAveragePositive": "0.7605107",
        "roBERTaAverageNeutral": "0.6937042",
        "roBERTaAverageNegative": "0.6247723",
        "roBERTaMedianPositive": "0.77843827",
        "roBERTaMedianNeutral": "0.70407003",
        "roBERTaMedianNegative": "0.6025307",
        "roBERTaStdPositive": "0.14866118",
        "roBERTaStdNeutral": "0.11705788",
        "roBERTaStdNegative": "0.12262373",
        "roBERTaPositiveSentencesCount": "108",
        "roBERTaNeutralSentencesCount": "635",
        "roBERTaNegativeSentencesCount": "67",
        "TotalSentencesCount": "810"
    },
    "Episode": "3",
    "Details": {
        "Description": "The hospital's med students are inspired by the doctors, who each look after their patients in their own ways. Lee Ik Joon gets a welcome visitor.",
        "Duration": "5177"
    },
    "UsefulStatistics": {
        "roBERTaModalMajorSentiment": "Neutral",
        "VADERModalMajorSentiment": "Neutral",
        "roBERTaTotalPositiveSentences": 170,
        "roBERTaTotalNeutralSentences": 1165,
        "roBERTaTotalNegativeSentences": 129,
        "VADERTotalPositiveSentences": 325,
        "VADERTotalNeutralSentences": 1038,
        "VADERTotalNegativeSentences": 101
    }
}